[
    {
        "title": "",
        "description": "",
        "optionName":"id",
        "optionValue": ""
    },
    {
        "title": "",
        "description": "",
        "optionName": "name",
        "optionValue": ""
    },
    {
        "title": "lei greeting",
        "description": "would you like a lei greeting?",
        "optionName": "greeting",
        "optionValue": "no"
    },
    {
        "title": "canoe ride",
        "description": "would you liek a Hawaiian canoe ride?",
        "optionName": "canoeRide",
        "optionValue": "no"
    },
    {
        "title": "behind the scenes tour",
        "description": "Would you like a behind the scenes tour of ha breath of life?",
        "optionName": "behindScenes",
        "optionValue": "no"
    },
    {
        "title": "souvenir DVD",
        "description": "Would you like to take home a souvenir dvd of ha breath of life?",
        "optionName": "dvd",
        "optionValue": "no"
    },
    {        "title": "Dessert optionValue ",
        "description": "Would you like a chocolate lava cake dessert during ha breath of life?",
        "optionName": "Dessert",
        "optionValue": "no"
    },
    {
                "title":"Tour guide",
        "description": "Would you like a personal tour guid during your visit to pcc?",
        "optionName": "tourGuide",
        "optionValue": "no"
    },
    {
                "title": "Dinner",
        "description": "which dining option do you prefer?",
        "optionName": "dinner",
        "optionValue": "no"
    },
    {
                "title": "Seating",
        "description": "Where would you like to sit for the ha breath of life show?",
        "optionName": "seatingLevel",
        "optionValue": "no"
    },
    {
               "title": "Tour combination",
        "description": "Would you like to compint",
        "optionName": "combo",
        "optionValue": "no"
    }
]